es_translator/__init__.py
es_translator/alpha.py
es_translator/cli.py
es_translator/config.py
es_translator/es.py
es_translator/es_translator.py
es_translator/interpreters/__init__.py
es_translator/interpreters/abstract.py
es_translator/interpreters/apertium/__init__.py
es_translator/interpreters/apertium/apertium.py
es_translator/interpreters/apertium/pairs.py
es_translator/interpreters/apertium/repository.py
es_translator/interpreters/argos/__init__.py
es_translator/interpreters/argos/argos.py
es_translator/logger.py
es_translator/monitor.py
es_translator/symlink.py
es_translator/tasks.py
es_translator/worker.py
es_translator-1.12.4.dist-info/WHEEL
es_translator-1.12.4.dist-info/LICENSE.md
es_translator-1.12.4.dist-info/entry_points.txt
es_translator-1.12.4.dist-info/METADATA
es_translator-1.12.4.dist-info/RECORD
