Metadata-Version: 2.1
Name: es-translator
Version: 1.12.4
Summary: A lazy yet bulletproof machine translation tool for Elasticsearch.
License: GNU AFFERO GENERAL PUBLIC LICENSE
Author: ICIJ
Author-email: engineering@icij.org
Requires-Python: >=3.9,<3.13
Classifier: License :: Other/Proprietary License
Classifier: Programming Language :: Python :: 3
Classifier: Programming Language :: Python :: 3.9
Classifier: Programming Language :: Python :: 3.10
Classifier: Programming Language :: Python :: 3.11
Requires-Dist: argostranslate (>=1.9.6,<2.0.0)
Requires-Dist: celery[redis] (>=5.3.1,<6.0.0)
Requires-Dist: click (>=8,<9)
Requires-Dist: coloredlogs
Requires-Dist: deb-pkg-tools (>=8.4,<9.0)
Requires-Dist: elasticsearch (>=7.10,<7.18)
Requires-Dist: elasticsearch-dsl (>=7,<8.0.0)
Requires-Dist: filelock (>=3.12.2,<4.0.0)
Requires-Dist: numpy (>=1.26.0)
Requires-Dist: plotext (>=5.3.2,<6.0.0)
Requires-Dist: pycountry (>=24,<25)
Requires-Dist: rich (>=13,<14)
Requires-Dist: sh (>=1.14,<2.0)
Requires-Dist: torch (>=2.3,<2.4)
Requires-Dist: urllib3 (>=1.26,<2.0)
